{
  "project_info": {
    "project_number": "1009542736288",
    "project_id": "aquascope-48ad2",
    "storage_bucket": "aquascope-48ad2.appspot.com"
  },
  "client": [
    {
      "client_info": {
        "mobilesdk_app_id": "1:1009542736288:android:62e294b6961f37ec919cc5",
        "android_client_info": {
          "package_name": "com.aquascope"
        }
      },
      "oauth_client": [
        {
          "client_id": "1009542736288-q2s4sbs2m89enuqbnse2bcukv94779t7.apps.googleusercontent.com",
          "client_type": 3
        }
      ],
      "api_key": [
        {
          "current_key": "AIzaSyCODML8iLgovmYPhMOBTLtgWbaASWY04Dk"
        }
      ],
      "services": {
        "appinvite_service": {
          "other_platform_oauth_client": [
            {
              "client_id": "1009542736288-q2s4sbs2m89enuqbnse2bcukv94779t7.apps.googleusercontent.com",
              "client_type": 3
            }
          ]
        }
      }
    }
  ],
  "configuration_version": "1"
}